et_xmlfile/__init__.py
et_xmlfile/xmlfile.py
et_xmlfile/tests/__init__.py
et_xmlfile/tests/common_imports.py
et_xmlfile/tests/helper.py
et_xmlfile/tests/test_incremental_xmlfile.py
et_xmlfile_2021-1.0.2.dist-info/METADATA
et_xmlfile_2021-1.0.2.dist-info/WHEEL
et_xmlfile_2021-1.0.2.dist-info/top_level.txt
et_xmlfile_2021-1.0.2.dist-info/RECORD
