Metadata-Version: 2.1
Name: et-xmlfile-2021
Version: 1.0.2
Summary: An implementation of lxml.xmlfile for the standard library
Home-page: https://github.com/compyman/et_xmlfile
Author: See ATUHORS.txt
Author-email: charlie.clark@clark-consulting.eu
License: MIT
Platform: UNKNOWN
Classifier: Development Status :: 5 - Production/Stable
Classifier: Operating System :: MacOS :: MacOS X
Classifier: Operating System :: Microsoft :: Windows
Classifier: Operating System :: POSIX
Classifier: License :: OSI Approved :: MIT License
Classifier: Programming Language :: Python
Classifier: Programming Language :: Python :: 2.6
Classifier: Programming Language :: Python :: 2.7
Classifier: Programming Language :: Python :: 3.3
Classifier: Programming Language :: Python :: 3.4
Requires-Python: >=2.6, !=3.2
